visibl_docs/__init__.py
visibl_docs/__main__.py
visibl_docs/auth.py
visibl_docs/cli.py
visibl_docs/main.py
visibl_docs/controllers/__init__.py
visibl_docs/controllers/terminal_controller.py
visibl_docs/controllers/ui_controller.py
visibl_docs/data/init_docs/_meta.ts
visibl_docs/data/init_docs/blog.mdx
visibl_docs/data/init_docs/foo.md
visibl_docs/data/init_docs/index.mdx
visibl_docs/data/init_docs/test.md
visibl_docs/data/init_docs/about/_meta.ts
visibl_docs/data/init_docs/about/a-page.mdx
visibl_docs/data/init_docs/about/acknowledgement.mdx
visibl_docs/data/init_docs/about/changelog.md
visibl_docs/data/init_docs/about/team.mdx
visibl_docs/data/init_docs/blog/_meta.tsx
visibl_docs/data/init_docs/blog/swr-v1.mdx
visibl_docs/data/init_docs/docs/404-500.mdx
visibl_docs/data/init_docs/docs/_meta.tsx
visibl_docs/data/init_docs/docs/advanced.mdx
visibl_docs/data/init_docs/docs/arguments.mdx
visibl_docs/data/init_docs/docs/callout.mdx
visibl_docs/data/init_docs/docs/change-log.mdx
visibl_docs/data/init_docs/docs/code-block-without-language.mdx
visibl_docs/data/init_docs/docs/conditional-fetching.md
visibl_docs/data/init_docs/docs/custom-header-ids.mdx
visibl_docs/data/init_docs/docs/data-fetching.mdx
visibl_docs/data/init_docs/docs/error-handling.mdx
visibl_docs/data/init_docs/docs/getting-started.mdx
visibl_docs/data/init_docs/docs/global-configuration.md
visibl_docs/data/init_docs/docs/middleware.mdx
visibl_docs/data/init_docs/docs/mutation.md
visibl_docs/data/init_docs/docs/options.mdx
visibl_docs/data/init_docs/docs/pagination.mdx
visibl_docs/data/init_docs/docs/prefetching.md
visibl_docs/data/init_docs/docs/raw-layout.mdx
visibl_docs/data/init_docs/docs/revalidation.mdx
visibl_docs/data/init_docs/docs/suspense.mdx
visibl_docs/data/init_docs/docs/typescript.mdx
visibl_docs/data/init_docs/docs/understanding.mdx
visibl_docs/data/init_docs/docs/with-nextjs.mdx
visibl_docs/data/init_docs/docs/wrap-toc-items.mdx
visibl_docs/data/init_docs/docs/advanced/_meta.tsx
visibl_docs-0.1.7.dist-info/METADATA
visibl_docs-0.1.7.dist-info/WHEEL
visibl_docs-0.1.7.dist-info/entry_points.txt
visibl_docs-0.1.7.dist-info/top_level.txt
visibl_docs-0.1.7.dist-info/RECORD
